pyRenderdocApp/__init__.py
pyRenderdocApp/_version.py
pyRenderdocApp/renderdoc_api.py
pyRenderdocApp/renderdoc_enums.py
pyRenderdocApp/lib/LICENSE.md
pyRenderdocApp/lib/__init__.py
pyRenderdocApp/lib/librenderdoc.so
pyRenderdocApp/lib/renderdoc.dll
pyRenderdocApp/lib/renderdoc_64.dll
pyrenderdocapp-0.1.5.dist-info/METADATA
pyrenderdocapp-0.1.5.dist-info/WHEEL
pyrenderdocapp-0.1.5.dist-info/licenses/LICENSE
pyrenderdocapp-0.1.5.dist-info/RECORD
